{
    "replace": true,
    "slots": [
        "sword/blade"
    ],
    "materialSlotCount": 1,
    "displayType": "major",
    "glyph": {
        "textureX": 32
    },
    "translation": {
        "primaryAttributes": {
            "generic.attack_damage": 3
        },
        "secondaryAttributes": {
            "generic.attack_speed": -1
        },
        "secondaryEffects": {
            "jab": -1
        },
        "tools": {
            "cut": [
                2,
                3
            ]
        },
        "durability": 4,
        "integrity": -3,
        "magicCapacity": 3
    },
    "outcomes": [
        {
            "materials": [
                "tetra:wood/",
                "tetra:stone/",
                "tetra:bone/"
            ],
            "moduleKey": "sword/short_blade",
            "moduleVariant": "short_blade/"
        },
        {
            "material": {
                "items": [
                    "kubejs:cobalt_sword_short_blade"
                ]
            },
            "countFactor": 1,
            "moduleKey": "sword/short_blade",
            "moduleVariant": "short_blade/cobalt",
            "requiredTools": {
                "hammer_dig": 5
            }
        },
        {
            "material": {
                "items": [
                    "kubejs:copper_sword_short_blade"
                ]
            },
            "countFactor": 1,
            "moduleKey": "sword/short_blade",
            "moduleVariant": "short_blade/copper",
            "requiredTools": {
                "hammer_dig": 1
            }
        },
        {
            "material": {
                "items": [
                    "kubejs:create_brass_sword_short_blade"
                ]
            },
            "countFactor": 1,
            "moduleKey": "sword/short_blade",
            "moduleVariant": "short_blade/create_brass",
            "requiredTools": {
                "hammer_dig": 2
            }
        },
        {
            "material": {
                "items": [
                    "kubejs:create_zinc_sword_short_blade"
                ]
            },
            "countFactor": 1,
            "moduleKey": "sword/short_blade",
            "moduleVariant": "short_blade/create_zinc",
            "requiredTools": {
                "hammer_dig": 2
            }
        },
        {
            "material": {
                "items": [
                    "kubejs:iron_sword_short_blade"
                ]
            },
            "countFactor": 1,
            "moduleKey": "sword/short_blade",
            "moduleVariant": "short_blade/iron",
            "requiredTools": {
                "hammer_dig": 2
            }
        },
        {
            "material": {
                "items": [
                    "kubejs:netherite_sword_short_blade"
                ]
            },
            "countFactor": 1,
            "moduleKey": "sword/short_blade",
            "moduleVariant": "short_blade/netherite",
            "requiredTools": {
                "hammer_dig": 4
            }
        },
        {
            "material": {
                "items": [
                    "kubejs:steel_sword_short_blade"
                ]
            },
            "countFactor": 1,
            "moduleKey": "sword/short_blade",
            "moduleVariant": "short_blade/steel",
            "requiredTools": {
                "hammer_dig": 3
            }
        },
        {
            "material": {
                "items": [
                    "kubejs:amethyst_sword_short_blade"
                ]
            },
            "countFactor": 1,
            "moduleKey": "sword/short_blade",
            "moduleVariant": "short_blade/amethyst",
            "requiredTools": {
                "hammer_dig": 3
            }
        },
        {
            "material": {
                "items": [
                    "kubejs:diamond_sword_short_blade"
                ]
            },
            "countFactor": 1,
            "moduleKey": "sword/short_blade",
            "moduleVariant": "short_blade/diamond",
            "requiredTools": {
                "hammer_dig": 3
            }
        },
        {
            "material": {
                "items": [
                    "kubejs:electrum_sword_short_blade"
                ]
            },
            "countFactor": 1,
            "moduleKey": "sword/short_blade",
            "moduleVariant": "short_blade/electrum",
            "requiredTools": {
                "hammer_dig": 2
            }
        },
        {
            "material": {
                "items": [
                    "kubejs:emerald_sword_short_blade"
                ]
            },
            "countFactor": 1,
            "moduleKey": "sword/short_blade",
            "moduleVariant": "short_blade/emerald",
            "requiredTools": {
                "hammer_dig": 3
            }
        },
        {
            "material": {
                "items": [
                    "kubejs:gold_sword_short_blade"
                ]
            },
            "countFactor": 1,
            "moduleKey": "sword/short_blade",
            "moduleVariant": "short_blade/gold",
            "requiredTools": {
                "hammer_dig": 1
            }
        },
        {
            "material": {
                "items": [
                    "kubejs:silver_sword_short_blade"
                ]
            },
            "countFactor": 1,
            "moduleKey": "sword/short_blade",
            "moduleVariant": "short_blade/silver",
            "requiredTools": {
                "hammer_dig": 4
            }
        }
    ]
}